threedi_schema/__init__.py
threedi_schema/scripts.py
threedi_schema/application/__init__.py
threedi_schema/application/errors.py
threedi_schema/application/schema.py
threedi_schema/application/threedi_database.py
threedi_schema/domain/__init__.py
threedi_schema/domain/constants.py
threedi_schema/domain/custom_types.py
threedi_schema/domain/indexes.py
threedi_schema/domain/models.py
threedi_schema/domain/views.py
threedi_schema/infrastructure/__init__.py
threedi_schema/infrastructure/spatial_index.py
threedi_schema/infrastructure/spatialite_versions.py
threedi_schema/infrastructure/views.py
threedi_schema/migrations/__init__.py
threedi_schema/migrations/env.py
threedi_schema/migrations/versions/0200_initial.py
threedi_schema/migrations/versions/0201_migrate_friction_type_4.py
threedi_schema/migrations/versions/0202_remove_unused_tables.py
threedi_schema/migrations/versions/0203_remove_unused_cols.py
threedi_schema/migrations/versions/0204_reset_nullable_foreign_keys.py
threedi_schema/migrations/versions/0205_settings_defaults.py
threedi_schema/migrations/versions/0206_control_structures.py
threedi_schema/migrations/versions/0207_fix_schema_constraints.py
threedi_schema/migrations/versions/0208_tables_settings.py
threedi_schema/migrations/versions/0209_remove_surface_type.py
threedi_schema/migrations/versions/0210_global_raster_values.py
threedi_schema/migrations/versions/0211_breach_and_exchange.py
threedi_schema/migrations/versions/0212_breach_and_exchange_properties.py
threedi_schema/migrations/versions/0213_connected_points_to_breaches.py
threedi_schema/migrations/versions/0214_drop_cpoints_levees.py
threedi_schema/migrations/versions/__init__.py
threedi_schema/tests/__init__.py
threedi_schema/tests/conftest.py
threedi_schema/tests/test_gpkg.py
threedi_schema/tests/test_migration_213.py
threedi_schema/tests/test_schema.py
threedi_schema/tests/test_spatalite_versions.py
threedi_schema/tests/data/__init__.py
threedi_schema-214.2.dist-info/LICENSE
threedi_schema-214.2.dist-info/METADATA
threedi_schema-214.2.dist-info/WHEEL
threedi_schema-214.2.dist-info/entry_points.txt
threedi_schema-214.2.dist-info/top_level.txt
threedi_schema-214.2.dist-info/RECORD
