Metadata-Version: 2.1
Name: threedi-schema
Version: 214.2
Summary: The schema of 3Di schematization files
Home-page: https://github.com/nens/threedi-schema
Author: Nelen & Schuurmans
Author-email: info@nelen-schuurmans.nl
License: MIT
Classifier: Programming Language :: Python
Classifier: Framework :: Django
Requires-Python: >=3.7
License-File: LICENSE
Requires-Dist: GeoAlchemy2 (!=0.11.*,>=0.9)
Requires-Dist: SQLAlchemy (>=1.3)
Requires-Dist: alembic (>=1.8)
Provides-Extra: cli
Requires-Dist: click ; extra == 'cli'
Provides-Extra: test
Requires-Dist: pytest ; extra == 'test'
Requires-Dist: pytest-cov ; extra == 'test'
